flask_fefset/__init__.py
flask_fefset/templates/footer.html
flask_fefset/templates/bootstrap4/base.html
flask_fefset/templates/bootstrap4/nav.html
flask_fefset/templates/bootstrap5/base.html
flask_fefset-0.0.5.dist-info/licenses/LICENSE
flask_fefset-0.0.5.dist-info/METADATA
flask_fefset-0.0.5.dist-info/WHEEL
flask_fefset-0.0.5.dist-info/top_level.txt
flask_fefset-0.0.5.dist-info/RECORD
